{
  "levels": [
    {
      "level": 1,
      "base_total_rewards": 20,
      "attributes": ["no_damage"],
      "rewards": {
        "spades": 90,
        "clubs": 10
      }
    },
    {
      "level": 2,
      "base_total_rewards": 50,
      "rewards": {
        "spades": 80,
        "clubs": 15,
        "keys": 1
      },
      "attack_length": 1.9
    },
    {
      "level": 3,
      "base_total_rewards": 100,
      "rewards": {
        "spades": 80,
        "clubs": 10
      },
      "attack_length": 1.7
    },
    {
      "level": 4,
      "base_total_rewards": 600,
      "rewards": {
        "spades": 75,
        "clubs": 15,
        "keys": 1
      },
      "attack_length": 1.4
    },
    {
      "level": 5,
      "base_total_rewards": 800,
      "rewards": {
        "spades": 70,
        "clubs": 20
      },
      "attack_length": 1.2
    },
    {
      "level": 6,
      "base_total_rewards": 1000,
      "rewards": {
        "spades": 65,
        "clubs": 20,
        "keys": 1
      },
      "attack_length": 1.0
    },
    {
      "level": 7,
      "base_total_rewards": 1300,
      "rewards": {
        "spades": 60,
        "clubs": 20
      },
      "attack_length": 0.8
    },
    {
      "level": 8,
      "base_total_rewards": 1600,
      "rewards": {
        "spades": 55,
        "clubs": 25,
        "keys": 1
      },
      "attack_length": 0.8
    },
    {
      "level": 9,
      "base_total_rewards": 2000,
      "rewards": {
        "spades": 50,
        "clubs": 25
      },
      "attack_length": 0.8
    },
    {
      "level": 10,
      "base_total_rewards": 2400,
      "rewards": {
        "spades": 45,
        "clubs": 30,
        "keys": 1
      },
      "attack_length": 0.6
    }
  ],
  "shop": [
    {
      "name": "ticket_img",
      "reward": "combatTickets",
      "cost": 100,
      "currency": "spades"
    },
    {
      "name": "\u2665\uFE0E",
      "reward": "hearts",
      "cost": 10,
      "currency": "spades"
    }
  ]
}
